README.md
setup.py
stream_monitor/__init__.py
stream_monitor.egg-info/PKG-INFO
stream_monitor.egg-info/SOURCES.txt
stream_monitor.egg-info/dependency_links.txt
stream_monitor.egg-info/entry_points.txt
stream_monitor.egg-info/not-zip-safe
stream_monitor.egg-info/requires.txt
stream_monitor.egg-info/top_level.txt