Metadata-Version: 1.0
Name: stream-monitor
Version: 2018.4.19.2211
Summary: monitoring and alerting program for data streams such as recording files that update regularly
Home-page: https://github.com/wdbm/stream_monitor
Author: Will Breaden Madden
Author-email: wbm@protonmail.ch
License: GPLv3
Platform: UNKNOWN
